[
  {
    "_folderName": "29CM 해피미타임",
    "title": "29CM 해피미타임",
    "year": "2026",
    "category": "Product Design / Photography",
    "description": "'Happy me time'을 테마로 한 라이프스타일 브랜드 화보로, 잔디밭과 공원, 오래된 상점 골목 등 편안한 일상 공간을 배경으로 스트라이프 후드와 도트 스커트, 블랙 톱 등 시즌 룩을 자연스럽게 담아냈다. 딸기 캐릭터가 담긴 니트 파우치와 키링 소품은 브랜드 특유의 아기자기한 무드를 완성하는 포인트로 함께 연출했다.\n\n미도리작업실은 촬영 콘셉트 기획부터 로케이션 헌팅, 인물 및 소품 촬영, 보정까지 전 과정을 진행하며 브랜드가 지향하는 따뜻하고 편안한 감성을 화보 전반에 일관되게 녹여냈다.",
    "meta": [
      [
        "분류",
        "제품 디자인 / 화보 촬영"
      ],
      [
        "연도",
        "2026"
      ],
      [
        "역할",
        "콘셉트 기획, 로케이션 헌팅, 촬영, 보정"
      ]
    ],
    "gridImage": "29CM 해피미타임/DSCF0345.jpg",
    "allImages": [
      "29CM 해피미타임/DSCF0345.jpg",
      "29CM 해피미타임/DSCF0806.jpg",
      "29CM 해피미타임/DSCF0225.jpg",
      "29CM 해피미타임/DSCF0580.jpg",
      "29CM 해피미타임/DSCF0609.jpg",
      "29CM 해피미타임/DSCF0755.jpg",
      "29CM 해피미타임/DSCF9837.jpg",
      "29CM 해피미타임/DSCF9994.jpg",
      "29CM 해피미타임/DSCF0796.jpg"
    ],
    "published": true
  },
  {
    "_folderName": "시원스쿨",
    "title": "시원스쿨",
    "year": "2024",
    "category": "",
    "description": "",
    "meta": [
      [
        "분류",
        ""
      ],
      [
        "연도",
        "2024"
      ],
      [
        "역할",
        ""
      ]
    ],
    "gridImage": "시원스쿨/DSCF1067.jpg",
    "allImages": [
      "시원스쿨/DSCF1067.jpg",
      "시원스쿨/DSCF1070.jpg",
      "시원스쿨/DSCF1073.jpg",
      "시원스쿨/DSCF1064.jpg",
      "시원스쿨/DSCF1066.jpg",
      "시원스쿨/DSCF1058.jpg",
      "시원스쿨/DSCF1104.jpg",
      "시원스쿨/DSCF1059.jpg",
      "시원스쿨/DSCF1071.jpg"
    ],
    "published": true
  },
  {
    "_folderName": "포트폴리오 위키",
    "title": "포트폴리오 위키",
    "year": "2024",
    "category": "",
    "description": "",
    "meta": [
      [
        "분류",
        ""
      ],
      [
        "연도",
        "2024"
      ],
      [
        "역할",
        ""
      ]
    ],
    "gridImage": "",
    "allImages": [],
    "published": false
  },
  {
    "_folderName": "화사",
    "title": "화사",
    "year": "2024",
    "category": "",
    "description": "",
    "meta": [
      [
        "분류",
        ""
      ],
      [
        "연도",
        "2024"
      ],
      [
        "역할",
        ""
      ]
    ],
    "gridImage": "화사/DSCF2624.jpg",
    "allImages": [
      "화사/DSCF2624.jpg",
      "화사/DSCF2625.jpg",
      "화사/DSCF2619.jpg",
      "화사/DSCF2552.jpg",
      "화사/DSCF2545.jpg",
      "화사/Frame 3.png",
      "화사/IMG_6288.jpg",
      "화사/DSCF2626.jpg",
      "화사/DSCF2590.jpg"
    ],
    "published": true
  }
]